crsEpsg/__init__.py
crsEpsg/crsEpsg.py
crsEpsg-0.0.3.dist-info/LICENSE
crsEpsg-0.0.3.dist-info/METADATA
crsEpsg-0.0.3.dist-info/WHEEL
crsEpsg-0.0.3.dist-info/top_level.txt
crsEpsg-0.0.3.dist-info/RECORD
